pymonad/__init__.py
pymonad/either.py
pymonad/list.py
pymonad/maybe.py
pymonad/monad.py
pymonad/monoid.py
pymonad/operators/__init__.py
pymonad/operators/either.py
pymonad/operators/list.py
pymonad/operators/maybe.py
pymonad/operators/operators.py
pymonad/operators/reader.py
pymonad/operators/state.py
pymonad/operators/writer.py
pymonad/promise.py
pymonad/reader.py
pymonad/state.py
pymonad/tools.py
pymonad/writer.py
boxx_pymonad-0.2.0.dist-info/LICENSE
boxx_pymonad-0.2.0.dist-info/WHEEL
boxx_pymonad-0.2.0.dist-info/METADATA
boxx_pymonad-0.2.0.dist-info/RECORD
