Metadata-Version: 2.1
Name: boxx-pymonad
Version: 0.2.0
Summary: My Implementation of pymonad package.
Home-page: https://wboxx1.github.io/boxx-pymonad
License: MIT
Author: Will Boxx
Author-email: wboxx1@gmail.com
Classifier: Development Status :: 2 - Pre-Alpha
Classifier: Intended Audience :: Developers
Classifier: License :: OSI Approved :: MIT License
Classifier: Natural Language :: English
Classifier: Programming Language :: Python :: 2
Classifier: Programming Language :: Python :: 2.7
Classifier: Programming Language :: Python :: 3
Classifier: Programming Language :: Python :: 3.4
Classifier: Programming Language :: Python :: 3.5
Classifier: Programming Language :: Python :: 3.6
Classifier: Programming Language :: Python :: 3.7
Classifier: Programming Language :: Python :: 3.8
Project-URL: Repository, https://github.com/wboxx1/boxx-pymonad
